{
  "player-walk-speed": 250.0,
  "monster-walk-speed": 250.0,
  "player-max-walk-speed": 150.0,
  "monster-max-walk-speed": 90.0,
  "ground-slowdown-factor": 0.6,
  "air-slowdown-factor": 0.95,
  "jump-speed": 300.0,
  "max-Y-speed": 400.0,
  "gravity": 881.25,
  "jump-gravity": 460,
  "bullet-hit-force": 1000,
  "bullet-start-speed": 900,
  "default-weapon-firing-frequency": 12,
  "friction": 0.1,
  "restitution": 0.5,
  "glue": 0.001,
  "character-frame-width": 32,
  "character-frame-height": 32,
  "player-texture-name": "player1_char_set",
  "monster-texture-name": "monster1_char_set",
  "monster-max-health": 12,
  "character-collision-rect": {
    "Left": 10,
    "Top": 0,
    "Width": 22,
    "Height": 32
  },
  "character-view-rect": {
    "Left": 5,
    "Top": 0,
    "Width": 27,
    "Height": 32
  },
  "lightmap-color": {
    "R": 10,
    "G": 10,
    "B": 10,
    "A": 255
  },
  "background-color": {
    "R": 255,
    "G": 255,
    "B": 255,
    "A": 255
  }
}